[
  {
    "name": "Star Sports 1",
    "id": "star1in",
    "logo": "https://raw.githubusercontent.com/abusaeeidx/Tv-Channel-Logo/heads/main/CricHD/runded/16-by-xfireflix.png",
    "link": "https://d15.epicquesthero.com:999/hls/star1in.m3u8?md5=EQeKYJT93bcnovK7C_pSjg&expires=1761328646",
    "referer": "https://stylisheleg4nt.com",
    "origin": "https://stylisheleg4nt.com"
  },
  {
    "name": "Star Sports 1 Hindi",
    "id": "starhindi",
    "logo": "https://raw.githubusercontent.com/abusaeeidx/Tv-Channel-Logo/heads/main/CricHD/runded/1-by-xfireflix.png",
    "link": "https://d15.epicquesthero.com:999/hls/starhindi.m3u8?md5=VUhuF7giDOm7f1_n5jmLxQ&expires=1761328646",
    "referer": "https://stylisheleg4nt.com",
    "origin": "https://stylisheleg4nt.com"
  },
  {
    "name": "PTV Sports",
    "id": "ptvpk",
    "logo": "https://raw.githubusercontent.com/abusaeeidx/Tv-Channel-Logo/heads/main/CricHD/runded/20-by-xfireflix.png",
    "link": "https://d15.epicquesthero.com:999/hls/ptvpk.m3u8?md5=XAFeA6u0XL1FgBI-muSBKg&expires=1761328647",
    "referer": "https://stylisheleg4nt.com",
    "origin": "https://stylisheleg4nt.com"
  },
  {
    "name": "Willow HD",
    "id": "willowusa",
    "logo": "https://raw.githubusercontent.com/abusaeeidx/Tv-Channel-Logo/heads/main/CricHD/runded/38-by-xfireflix.png",
    "link": "https://d15.epicquesthero.com:999/hls/willowusa.m3u8?md5=d2A2YMe9_lmC-8hBc8-pog&expires=1761328647",
    "referer": "https://stylisheleg4nt.com",
    "origin": "https://stylisheleg4nt.com"
  },
  {
    "name": "Willow HD 2",
    "id": "willowextra",
    "logo": "https://raw.githubusercontent.com/abusaeeidx/Tv-Channel-Logo/heads/main/CricHD/runded/8-by-xfireflix.png",
    "link": "https://d15.epicquesthero.com:999/hls/willowextra.m3u8?md5=HcsymEP4GgzrjcnSAH5Q0Q&expires=1761328647",
    "referer": "https://stylisheleg4nt.com",
    "origin": "https://stylisheleg4nt.com"
  },
  {
    "name": "Ten Sports",
    "id": "tenspk",
    "logo": "https://raw.githubusercontent.com/abusaeeidx/Tv-Channel-Logo/heads/main/CricHD/runded/10-by-xfireflix.png",
    "link": "https://d15.epicquesthero.com:999/hls/tenspk.m3u8?md5=fP1wjkLftgZllGuVZSxF6g&expires=1761328647",
    "referer": "https://stylisheleg4nt.com",
    "origin": "https://stylisheleg4nt.com"
  },
  {
    "name": "A Sports HD",
    "id": "asportshd",
    "logo": "https://raw.githubusercontent.com/abusaeeidx/Tv-Channel-Logo/heads/main/CricHD/runded/12-by-xfireflix.png",
    "link": "https://d15.epicquesthero.com:999/hls/asportshd.m3u8?md5=qHunvcJrwY08yDWH4IftCQ&expires=1761328647",
    "referer": "https://stylisheleg4nt.com",
    "origin": "https://stylisheleg4nt.com"
  },
  {
    "name": "Sky Sports Cricket",
    "id": "skyscric",
    "logo": "https://raw.githubusercontent.com/abusaeeidx/Tv-Channel-Logo/heads/main/CricHD/runded/9-by-xfireflix.png",
    "link": "https://d15.epicquesthero.com:999/hls/skyscric.m3u8?md5=6WTwWLtV580W7Z71VzjVPw&expires=1761328647",
    "referer": "https://stylisheleg4nt.com",
    "origin": "https://stylisheleg4nt.com"
  },
  {
    "name": "Sky Sports Main Event",
    "id": "skysme",
    "logo": "https://raw.githubusercontent.com/abusaeeidx/Tv-Channel-Logo/heads/main/CricHD/runded/18-by-xfireflix.png",
    "link": "https://d15.epicquesthero.com:999/hls/skysme.m3u8?md5=dLfCT3qDH_05kL5OJVHWHg&expires=1761328648",
    "referer": "https://stylisheleg4nt.com",
    "origin": "https://stylisheleg4nt.com"
  },
  {
    "name": "TNT 1",
    "id": "bbtsp1",
    "logo": "https://raw.githubusercontent.com/abusaeeidx/Tv-Channel-Logo/heads/main/CricHD/runded/tnt.png",
    "link": "https://d15.epicquesthero.com:999/hls/bbtsp1.m3u8?md5=e_FY0Mr8XzONBHijpZcWdQ&expires=1761328648",
    "referer": "https://stylisheleg4nt.com",
    "origin": "https://stylisheleg4nt.com"
  },
  {
    "name": "TNT 2",
    "id": "bbtsp2",
    "logo": "https://raw.githubusercontent.com/abusaeeidx/Tv-Channel-Logo/heads/main/CricHD/runded/tnt.png",
    "link": "https://d15.epicquesthero.com:999/hls/bbtsp2.m3u8?md5=Ud7K4JAg0rVPbm6_ZqkBHA&expires=1761328648",
    "referer": "https://stylisheleg4nt.com",
    "origin": "https://stylisheleg4nt.com"
  },
  {
    "name": "TNT 3",
    "id": "bbtsp3",
    "logo": "https://raw.githubusercontent.com/abusaeeidx/Tv-Channel-Logo/heads/main/CricHD/runded/tnt.png",
    "link": "https://d15.epicquesthero.com:999/hls/bbtsp3.m3u8?md5=W6LG_RK9HD5YEZ4s1l6Kww&expires=1761328648",
    "referer": "https://stylisheleg4nt.com",
    "origin": "https://stylisheleg4nt.com"
  },
  {
    "name": "TNT 4",
    "id": "bbtespn",
    "logo": "https://raw.githubusercontent.com/abusaeeidx/Tv-Channel-Logo/heads/main/CricHD/runded/tnt.png",
    "link": "https://d15.epicquesthero.com:999/hls/bbtespn.m3u8?md5=EUv8mZ1X2YPlirp8ogKwzA&expires=1761328648",
    "referer": "https://stylisheleg4nt.com",
    "origin": "https://stylisheleg4nt.com"
  },
  {
    "name": "Sky Sports 1",
    "id": "sky1nz",
    "logo": "https://raw.githubusercontent.com/abusaeeidx/Tv-Channel-Logo/heads/main/CricHD/runded/56-by-xfireflix.png",
    "link": "https://d15.epicquesthero.com:999/hls/sky1nz.m3u8?md5=paSnz0HpM6Ik1Hy9T46iZg&expires=1761328648",
    "referer": "https://stylisheleg4nt.com",
    "origin": "https://stylisheleg4nt.com"
  },
  {
    "name": "Sky Sports 2",
    "id": "sky2nz",
    "logo": "https://raw.githubusercontent.com/abusaeeidx/Tv-Channel-Logo/heads/main/CricHD/runded/56-by-xfireflix.png",
    "link": "https://d15.epicquesthero.com:999/hls/sky2nz.m3u8?md5=wVvxxuK1MSHJy2PwAzdgsw&expires=1761328648",
    "referer": "https://stylisheleg4nt.com",
    "origin": "https://stylisheleg4nt.com"
  },
  {
    "name": "Sky Sports 3",
    "id": "sky3nz",
    "logo": "https://raw.githubusercontent.com/abusaeeidx/Tv-Channel-Logo/heads/main/CricHD/runded/56-by-xfireflix.png",
    "link": "https://d15.epicquesthero.com:999/hls/sky3nz.m3u8?md5=6XcqeNjorE-o-ostqSmOjA&expires=1761328649",
    "referer": "https://stylisheleg4nt.com",
    "origin": "https://stylisheleg4nt.com"
  },
  {
    "name": "Sky Sports 4",
    "id": "sky4nz",
    "logo": "https://raw.githubusercontent.com/abusaeeidx/Tv-Channel-Logo/heads/main/CricHD/runded/56-by-xfireflix.png",
    "link": "https://d15.epicquesthero.com:999/hls/sky4nz.m3u8?md5=ASZK_069n9eOLIFg1SYkXw&expires=1761328649",
    "referer": "https://stylisheleg4nt.com",
    "origin": "https://stylisheleg4nt.com"
  },
  {
    "name": "Sky Sports 5",
    "id": "sky5nz",
    "logo": "https://raw.githubusercontent.com/abusaeeidx/Tv-Channel-Logo/heads/main/CricHD/runded/56-by-xfireflix.png",
    "link": "https://d15.epicquesthero.com:999/hls/sky5nz.m3u8?md5=q79k-vkoIJeQ2xK8VELvzw&expires=1761328649",
    "referer": "https://stylisheleg4nt.com",
    "origin": "https://stylisheleg4nt.com"
  },
  {
    "name": "Sky Sports 6",
    "id": "sky6nz",
    "logo": "https://raw.githubusercontent.com/abusaeeidx/Tv-Channel-Logo/heads/main/CricHD/runded/56-by-xfireflix.png",
    "link": "https://d15.epicquesthero.com:999/hls/sky6nz.m3u8?md5=yD0aUaHlEbuTeUA7hqhtjQ&expires=1761328649",
    "referer": "https://stylisheleg4nt.com",
    "origin": "https://stylisheleg4nt.com"
  },
  {
    "name": "Sky Sports 7",
    "id": "sky7nz",
    "logo": "https://raw.githubusercontent.com/abusaeeidx/Tv-Channel-Logo/heads/main/CricHD/runded/56-by-xfireflix.png",
    "link": "https://d15.epicquesthero.com:999/hls/sky7nz.m3u8?md5=OnWN3w-Ix9dXajSL569Q3Q&expires=1761328649",
    "referer": "https://stylisheleg4nt.com",
    "origin": "https://stylisheleg4nt.com"
  },
  {
    "name": "Sky Sports 8",
    "id": "sky8nz",
    "logo": "https://raw.githubusercontent.com/abusaeeidx/Tv-Channel-Logo/heads/main/CricHD/runded/56-by-xfireflix.png",
    "link": "https://d15.epicquesthero.com:999/hls/sky8nz.m3u8?md5=u64E2BiOp-JHBY1PeK4iGA&expires=1761328649",
    "referer": "https://stylisheleg4nt.com",
    "origin": "https://stylisheleg4nt.com"
  },
  {
    "name": "Sky Sports 9",
    "id": "sky9nz",
    "logo": "https://raw.githubusercontent.com/abusaeeidx/Tv-Channel-Logo/heads/main/CricHD/runded/56-by-xfireflix.png",
    "link": "https://d15.epicquesthero.com:999/hls/sky9nz.m3u8?md5=zJOXhpx4XWxY3wu83T85dg&expires=1761328650",
    "referer": "https://stylisheleg4nt.com",
    "origin": "https://stylisheleg4nt.com"
  },
  {
    "name": "Sky Cinema",
    "id": "skysme",
    "logo": "https://raw.githubusercontent.com/abusaeeidx/Tv-Channel-Logo/heads/main/CricHD/runded/skycinema.png",
    "link": "https://d15.epicquesthero.com:999/hls/skysme.m3u8?md5=gTyII0a_kzG9-7a8xnMXYA&expires=1761328650",
    "referer": "https://stylisheleg4nt.com",
    "origin": "https://stylisheleg4nt.com"
  },
  {
    "name": "Sky Sports Action",
    "id": "skysact",
    "logo": "https://raw.githubusercontent.com/abusaeeidx/Tv-Channel-Logo/heads/main/CricHD/runded/1745007829332.png",
    "link": "https://d15.epicquesthero.com:999/hls/skysact.m3u8?md5=o2wMA0hceKqzCC0iVe6-nQ&expires=1761328650",
    "referer": "https://stylisheleg4nt.com",
    "origin": "https://stylisheleg4nt.com"
  },
  {
    "name": "Sky Sports Golf",
    "id": "skysgol",
    "logo": "https://raw.githubusercontent.com/abusaeeidx/Tv-Channel-Logo/heads/main/CricHD/runded/1745008055327.png",
    "link": "https://d15.epicquesthero.com:999/hls/skysgol.m3u8?md5=V2s0-zLYoUrIeV81xudaLw&expires=1761328672",
    "referer": "https://stylisheleg4nt.com",
    "origin": "https://stylisheleg4nt.com"
  },
  {
    "name": "Sky Sports Premier League",
    "id": "skysprem",
    "logo": "https://raw.githubusercontent.com/abusaeeidx/Tv-Channel-Logo/heads/main/CricHD/runded/43-by-xfireflix.png",
    "link": "https://d15.epicquesthero.com:999/hls/skysprem.m3u8?md5=ICFHHr8btopm4TR5sNKr1g&expires=1761328673",
    "referer": "https://stylisheleg4nt.com",
    "origin": "https://stylisheleg4nt.com"
  },
  {
    "name": "Sky Sports Football",
    "id": "skysfott",
    "logo": "https://raw.githubusercontent.com/abusaeeidx/Tv-Channel-Logo/heads/main/CricHD/runded/44-by-xfireflix.png",
    "link": "https://d15.epicquesthero.com:999/hls/skysfott.m3u8?md5=sw1WOY535wT9x-x4XiJf1Q&expires=1761328673",
    "referer": "https://stylisheleg4nt.com",
    "origin": "https://stylisheleg4nt.com"
  },
  {
    "name": "Sky Sports Plus",
    "id": "skysare",
    "logo": "https://raw.githubusercontent.com/abusaeeidx/Tv-Channel-Logo/heads/main/CricHD/runded/1745008347584.png",
    "link": "https://d15.epicquesthero.com:999/hls/skysare.m3u8?md5=HYDJIsGMfHWzyab5qeO1kw&expires=1761328673",
    "referer": "https://stylisheleg4nt.com",
    "origin": "https://stylisheleg4nt.com"
  },
  {
    "name": "Sky Sports F1",
    "id": "skysfor1",
    "logo": "https://raw.githubusercontent.com/abusaeeidx/Tv-Channel-Logo/heads/main/CricHD/runded/1745008468637.png",
    "link": "https://d15.epicquesthero.com:999/hls/skysfor1.m3u8?md5=ZsnfqI3un2KUpGjhToKJ1A&expires=1761328673",
    "referer": "https://stylisheleg4nt.com",
    "origin": "https://stylisheleg4nt.com"
  },
  {
    "name": "LaLiGA",
    "id": "laligauk",
    "logo": "https://raw.githubusercontent.com/abusaeeidx/Tv-Channel-Logo/heads/main/CricHD/runded/19-by-xfireflix.png",
    "link": "https://d15.epicquesthero.com:999/hls/laligauk.m3u8?md5=s-eb0Wn1cTzkLK83hJRBzg&expires=1761328673",
    "referer": "https://stylisheleg4nt.com",
    "origin": "https://stylisheleg4nt.com"
  },
  {
    "name": "Premier Sports 1",
    "id": "premieruk",
    "logo": "https://raw.githubusercontent.com/abusaeeidx/Tv-Channel-Logo/heads/main/CricHD/runded/31-by-xfireflix.png",
    "link": "https://d15.epicquesthero.com:999/hls/premieruk.m3u8?md5=Zot6NIqK8ki2nahZ2D7zRQ&expires=1761328673",
    "referer": "https://stylisheleg4nt.com",
    "origin": "https://stylisheleg4nt.com"
  },
  {
    "name": "Premier Sports 2",
    "id": "hdchnl2",
    "logo": "https://raw.githubusercontent.com/abusaeeidx/Tv-Channel-Logo/heads/main/CricHD/runded/31-by-xfireflix.png",
    "link": "https://d15.epicquesthero.com:999/hls/hdchnl2.m3u8?md5=Cikmy0RsN6ohG2dWHmjZAg&expires=1761328673",
    "referer": "https://stylisheleg4nt.com",
    "origin": "https://stylisheleg4nt.com"
  },
  {
    "name": "Super Football",
    "id": "superfotball",
    "logo": "https://raw.githubusercontent.com/abusaeeidx/Tv-Channel-Logo/heads/main/CricHD/runded/34-by-xfireflix.png",
    "link": "https://d15.epicquesthero.com:999/hls/superfotball.m3u8?md5=pmpY2AMEoVIVl21dLuOSkw&expires=1761328674",
    "referer": "https://stylisheleg4nt.com",
    "origin": "https://stylisheleg4nt.com"
  },
  {
    "name": "Super Premier League",
    "id": "superpremier",
    "logo": "https://raw.githubusercontent.com/abusaeeidx/Tv-Channel-Logo/heads/main/CricHD/runded/1745008781606.png",
    "link": "https://d15.epicquesthero.com:999/hls/superpremier.m3u8?md5=vVgx77D3ZT4MZuze2_4mOg&expires=1761328674",
    "referer": "https://stylisheleg4nt.com",
    "origin": "https://stylisheleg4nt.com"
  },
  {
    "name": "Astro Cricket",
    "id": "fox501",
    "logo": "https://raw.githubusercontent.com/abusaeeidx/Tv-Channel-Logo/heads/main/CricHD/runded/1745008895589.png",
    "link": "https://d15.epicquesthero.com:999/hls/fox501.m3u8?md5=eqOqRVleKhKqilNiJZdTKw&expires=1761328674",
    "referer": "https://stylisheleg4nt.com",
    "origin": "https://stylisheleg4nt.com"
  },
  {
    "name": "ESPN 1",
    "id": "espnusa",
    "logo": "https://raw.githubusercontent.com/abusaeeidx/Tv-Channel-Logo/heads/main/CricHD/runded/17-by-xfireflix.png",
    "link": "https://d15.epicquesthero.com:999/hls/espnusa.m3u8?md5=ACU0qWZ-bj4Nyg_WCnrBOw&expires=1761328674",
    "referer": "https://stylisheleg4nt.com",
    "origin": "https://stylisheleg4nt.com"
  },
  {
    "name": "ESPN 2",
    "id": "espn2",
    "logo": "https://raw.githubusercontent.com/abusaeeidx/Tv-Channel-Logo/heads/main/CricHD/runded/17-by-xfireflix.png",
    "link": "https://d15.epicquesthero.com:999/hls/espn2.m3u8?md5=nZI4XyNbZpNhbucuThxG_A&expires=1761328674",
    "referer": "https://stylisheleg4nt.com",
    "origin": "https://stylisheleg4nt.com"
  },
  {
    "name": "Sky Sports Arena",
    "id": "skysare",
    "logo": "https://raw.githubusercontent.com/abusaeeidx/Tv-Channel-Logo/heads/main/CricHD/runded/1745007829327.png",
    "link": "https://d15.epicquesthero.com:999/hls/skysare.m3u8?md5=5zQyIgVSBTEwg1P9_EPlLA&expires=1761328674",
    "referer": "https://stylisheleg4nt.com",
    "origin": "https://stylisheleg4nt.com"
  },
  {
    "name": "Sky Sports Mix",
    "id": "skysmixx",
    "logo": "https://raw.githubusercontent.com/abusaeeidx/Tv-Channel-Logo/heads/main/CricHD/runded/13-by-xfireflix.png",
    "link": "https://d15.epicquesthero.com:999/hls/skysmixx.m3u8?md5=3eDOs8AhWBZSAnilemAxdQ&expires=1761328674",
    "referer": "https://stylisheleg4nt.com",
    "origin": "https://stylisheleg4nt.com"
  },
  {
    "name": "Sky Sports Tennis",
    "id": "skystennis",
    "logo": "https://raw.githubusercontent.com/abusaeeidx/Tv-Channel-Logo/heads/main/CricHD/runded/1745009085794.png",
    "link": "https://d15.epicquesthero.com:999/hls/skystennis.m3u8?md5=ktpjk6WK40xq5fGRMe_Mww&expires=1761328675",
    "referer": "https://stylisheleg4nt.com",
    "origin": "https://stylisheleg4nt.com"
  },
  {
    "name": "Fox Cricket 501 HD",
    "id": "fox501",
    "logo": "https://raw.githubusercontent.com/abusaeeidx/Tv-Channel-Logo/heads/main/CricHD/runded/6-by-xfireflix.png",
    "link": "https://d15.epicquesthero.com:999/hls/fox501.m3u8?md5=UYy89sNZY5RLEdV2FA5HUQ&expires=1761328675",
    "referer": "https://stylisheleg4nt.com",
    "origin": "https://stylisheleg4nt.com"
  },
  {
    "name": "Sony Sports3",
    "id": "ten1hd",
    "logo": "https://raw.githubusercontent.com/abusaeeidx/Tv-Channel-Logo/heads/main/CricHD/runded/1000173192-modified.png",
    "link": "https://d15.epicquesthero.com:999/hls/ten1hd.m3u8?md5=l4fimCHQ_89Bjxy4K4NtGA&expires=1761328675",
    "referer": "https://stylisheleg4nt.com",
    "origin": "https://stylisheleg4nt.com"
  }
]