[
    {
        "name": "Star Sports 1",
        "id": "star1in",
        "logo": "https://raw.githubusercontent.com/abusaeeidx/Tv-Channel-Logo/heads/main/CricHD/runded/16-by-xfireflix.png",
        "link": "https://d15.epicquesthero.com:999/hls/star1in.m3u8?md5=FknjMwnno2PS92LCy-1-7A&expires=1759962396",
        "referer": "https://stylisheleg4nt.com",
        "origin": "https://stylisheleg4nt.com"
    },
    {
        "name": "Star Sports 1 Hindi",
        "id": "starhindi",
        "logo": "https://raw.githubusercontent.com/abusaeeidx/Tv-Channel-Logo/heads/main/CricHD/runded/1-by-xfireflix.png",
        "link": "https://d15.epicquesthero.com:999/hls/starhindi.m3u8?md5=G5zRpeAjeYOB0NwmmNBnag&expires=1759962396",
        "referer": "https://stylisheleg4nt.com",
        "origin": "https://stylisheleg4nt.com"
    },
    {
        "name": "PTV Sports",
        "id": "ptvpk",
        "logo": "https://raw.githubusercontent.com/abusaeeidx/Tv-Channel-Logo/heads/main/CricHD/runded/20-by-xfireflix.png",
        "link": "https://d15.epicquesthero.com:999/hls/ptvpk.m3u8?md5=mwOW3Tre6DtKX8H8gCxKpw&expires=1759962396",
        "referer": "https://stylisheleg4nt.com",
        "origin": "https://stylisheleg4nt.com"
    },
    {
        "name": "Willow HD",
        "id": "willowusa",
        "logo": "https://raw.githubusercontent.com/abusaeeidx/Tv-Channel-Logo/heads/main/CricHD/runded/38-by-xfireflix.png",
        "link": "https://d15.epicquesthero.com:999/hls/willowusa.m3u8?md5=aMD92cDaQNDylD1QO465zQ&expires=1759962396",
        "referer": "https://stylisheleg4nt.com",
        "origin": "https://stylisheleg4nt.com"
    },
    {
        "name": "Willow HD 2",
        "id": "willowextra",
        "logo": "https://raw.githubusercontent.com/abusaeeidx/Tv-Channel-Logo/heads/main/CricHD/runded/8-by-xfireflix.png",
        "link": "https://d15.epicquesthero.com:999/hls/willowextra.m3u8?md5=Ydm0CS0mHR0t1ol9IzWHpQ&expires=1759962396",
        "referer": "https://stylisheleg4nt.com",
        "origin": "https://stylisheleg4nt.com"
    },
    {
        "name": "Ten Sports",
        "id": "tenspk",
        "logo": "https://raw.githubusercontent.com/abusaeeidx/Tv-Channel-Logo/heads/main/CricHD/runded/10-by-xfireflix.png",
        "link": "https://d15.epicquesthero.com:999/hls/tenspk.m3u8?md5=8xr25sen463HDaxax--UAA&expires=1759962396",
        "referer": "https://stylisheleg4nt.com",
        "origin": "https://stylisheleg4nt.com"
    },
    {
        "name": "A Sports HD",
        "id": "asportshd",
        "logo": "https://raw.githubusercontent.com/abusaeeidx/Tv-Channel-Logo/heads/main/CricHD/runded/12-by-xfireflix.png",
        "link": "https://d15.epicquesthero.com:999/hls/asportshd.m3u8?md5=mWfQsU76CCEb_UNQa1RGQA&expires=1759962396",
        "referer": "https://stylisheleg4nt.com",
        "origin": "https://stylisheleg4nt.com"
    },
    {
        "name": "Sky Sports Cricket",
        "id": "skyscric",
        "logo": "https://raw.githubusercontent.com/abusaeeidx/Tv-Channel-Logo/heads/main/CricHD/runded/9-by-xfireflix.png",
        "link": "https://d15.epicquesthero.com:999/hls/skyscric.m3u8?md5=ELOzwUPLxw1xDqweXo0snA&expires=1759962396",
        "referer": "https://stylisheleg4nt.com",
        "origin": "https://stylisheleg4nt.com"
    },
    {
        "name": "Sky Sports Main Event",
        "id": "skysme",
        "logo": "https://raw.githubusercontent.com/abusaeeidx/Tv-Channel-Logo/heads/main/CricHD/runded/18-by-xfireflix.png",
        "link": "https://d15.epicquesthero.com:999/hls/skysme.m3u8?md5=avWEbRGK3BlrxXl6jYgMiA&expires=1759962396",
        "referer": "https://stylisheleg4nt.com",
        "origin": "https://stylisheleg4nt.com"
    },
    {
        "name": "TNT 1",
        "id": "bbtsp1",
        "logo": "https://raw.githubusercontent.com/abusaeeidx/Tv-Channel-Logo/heads/main/CricHD/runded/tnt.png",
        "link": "https://d15.epicquesthero.com:999/hls/bbtsp1.m3u8?md5=3AHj5qQZvmy55nQpIn4VrQ&expires=1759962396",
        "referer": "https://stylisheleg4nt.com",
        "origin": "https://stylisheleg4nt.com"
    },
    {
        "name": "TNT 2",
        "id": "bbtsp2",
        "logo": "https://raw.githubusercontent.com/abusaeeidx/Tv-Channel-Logo/heads/main/CricHD/runded/tnt.png",
        "link": "https://d15.epicquesthero.com:999/hls/bbtsp2.m3u8?md5=Qqc-Ov7GFa9b-W-crL8snA&expires=1759962396",
        "referer": "https://stylisheleg4nt.com",
        "origin": "https://stylisheleg4nt.com"
    },
    {
        "name": "TNT 3",
        "id": "bbtsp3",
        "logo": "https://raw.githubusercontent.com/abusaeeidx/Tv-Channel-Logo/heads/main/CricHD/runded/tnt.png",
        "link": "https://d15.epicquesthero.com:999/hls/bbtsp3.m3u8?md5=Kh9etLGJz85N5hoi2SPTvA&expires=1759962397",
        "referer": "https://stylisheleg4nt.com",
        "origin": "https://stylisheleg4nt.com"
    },
    {
        "name": "TNT 4",
        "id": "bbtespn",
        "logo": "https://raw.githubusercontent.com/abusaeeidx/Tv-Channel-Logo/heads/main/CricHD/runded/tnt.png",
        "link": "https://d15.epicquesthero.com:999/hls/bbtespn.m3u8?md5=FU5zk7tk20ORhd5KUCa6YQ&expires=1759962397",
        "referer": "https://stylisheleg4nt.com",
        "origin": "https://stylisheleg4nt.com"
    },
    {
        "name": "Sky Sports 1",
        "id": "sky1nz",
        "logo": "https://raw.githubusercontent.com/abusaeeidx/Tv-Channel-Logo/heads/main/CricHD/runded/56-by-xfireflix.png",
        "link": "https://d15.epicquesthero.com:999/hls/sky1nz.m3u8?md5=AGuBjANzB_yAKHs81W_Z-A&expires=1759962397",
        "referer": "https://stylisheleg4nt.com",
        "origin": "https://stylisheleg4nt.com"
    },
    {
        "name": "Sky Sports 2",
        "id": "sky2nz",
        "logo": "https://raw.githubusercontent.com/abusaeeidx/Tv-Channel-Logo/heads/main/CricHD/runded/56-by-xfireflix.png",
        "link": "https://d15.epicquesthero.com:999/hls/sky2nz.m3u8?md5=GeQTEuaB1GukznIE4oEP6w&expires=1759962397",
        "referer": "https://stylisheleg4nt.com",
        "origin": "https://stylisheleg4nt.com"
    },
    {
        "name": "Sky Sports 3",
        "id": "sky3nz",
        "logo": "https://raw.githubusercontent.com/abusaeeidx/Tv-Channel-Logo/heads/main/CricHD/runded/56-by-xfireflix.png",
        "link": "https://d15.epicquesthero.com:999/hls/sky3nz.m3u8?md5=TtojelDPM8uh2BR2cHtwcg&expires=1759962397",
        "referer": "https://stylisheleg4nt.com",
        "origin": "https://stylisheleg4nt.com"
    },
    {
        "name": "Sky Sports 4",
        "id": "sky4nz",
        "logo": "https://raw.githubusercontent.com/abusaeeidx/Tv-Channel-Logo/heads/main/CricHD/runded/56-by-xfireflix.png",
        "link": "https://d15.epicquesthero.com:999/hls/sky4nz.m3u8?md5=njH2vqqmZaNAxez11_gM4Q&expires=1759962397",
        "referer": "https://stylisheleg4nt.com",
        "origin": "https://stylisheleg4nt.com"
    },
    {
        "name": "Sky Sports 5",
        "id": "sky5nz",
        "logo": "https://raw.githubusercontent.com/abusaeeidx/Tv-Channel-Logo/heads/main/CricHD/runded/56-by-xfireflix.png",
        "link": "https://d15.epicquesthero.com:999/hls/sky5nz.m3u8?md5=whyybdpCpAVMcbWTQPBo_A&expires=1759962397",
        "referer": "https://stylisheleg4nt.com",
        "origin": "https://stylisheleg4nt.com"
    },
    {
        "name": "Sky Sports 6",
        "id": "sky6nz",
        "logo": "https://raw.githubusercontent.com/abusaeeidx/Tv-Channel-Logo/heads/main/CricHD/runded/56-by-xfireflix.png",
        "link": "https://d15.epicquesthero.com:999/hls/sky6nz.m3u8?md5=94YzksWvLNTSLeF0mY1VyA&expires=1759962397",
        "referer": "https://stylisheleg4nt.com",
        "origin": "https://stylisheleg4nt.com"
    },
    {
        "name": "Sky Sports 7",
        "id": "sky7nz",
        "logo": "https://raw.githubusercontent.com/abusaeeidx/Tv-Channel-Logo/heads/main/CricHD/runded/56-by-xfireflix.png",
        "link": "https://d15.epicquesthero.com:999/hls/sky7nz.m3u8?md5=MmQAqEnlCSdHYfMncS_AnQ&expires=1759962397",
        "referer": "https://stylisheleg4nt.com",
        "origin": "https://stylisheleg4nt.com"
    },
    {
        "name": "Sky Sports 8",
        "id": "sky8nz",
        "logo": "https://raw.githubusercontent.com/abusaeeidx/Tv-Channel-Logo/heads/main/CricHD/runded/56-by-xfireflix.png",
        "link": "https://d15.epicquesthero.com:999/hls/sky8nz.m3u8?md5=qX_Tjo7fnbTKv6tPHaS0WQ&expires=1759962397",
        "referer": "https://stylisheleg4nt.com",
        "origin": "https://stylisheleg4nt.com"
    },
    {
        "name": "Sky Sports 9",
        "id": "sky9nz",
        "logo": "https://raw.githubusercontent.com/abusaeeidx/Tv-Channel-Logo/heads/main/CricHD/runded/56-by-xfireflix.png",
        "link": "https://d15.epicquesthero.com:999/hls/sky9nz.m3u8?md5=-idvkNd2YCFddIfnY_6e0g&expires=1759962397",
        "referer": "https://stylisheleg4nt.com",
        "origin": "https://stylisheleg4nt.com"
    },
    {
        "name": "Sky Cinema",
        "id": "skysme",
        "logo": "https://raw.githubusercontent.com/abusaeeidx/Tv-Channel-Logo/heads/main/CricHD/runded/skycinema.png",
        "link": "https://d15.epicquesthero.com:999/hls/skysme.m3u8?md5=oe-zDV9AzJDA7-Gym_J6Sg&expires=1759962398",
        "referer": "https://stylisheleg4nt.com",
        "origin": "https://stylisheleg4nt.com"
    },
    {
        "name": "Sky Sports Action",
        "id": "skysact",
        "logo": "https://raw.githubusercontent.com/abusaeeidx/Tv-Channel-Logo/heads/main/CricHD/runded/1745007829332.png",
        "link": "https://d15.epicquesthero.com:999/hls/skysact.m3u8?md5=mSRya0INi8YvGl_RG_WeyQ&expires=1759962398",
        "referer": "https://stylisheleg4nt.com",
        "origin": "https://stylisheleg4nt.com"
    },
    {
        "name": "Sky Sports Golf",
        "id": "skysgol",
        "logo": "https://raw.githubusercontent.com/abusaeeidx/Tv-Channel-Logo/heads/main/CricHD/runded/1745008055327.png",
        "link": "https://d15.epicquesthero.com:999/hls/skysgol.m3u8?md5=PmNEffdoR_V84XKLA5F41g&expires=1759962398",
        "referer": "https://stylisheleg4nt.com",
        "origin": "https://stylisheleg4nt.com"
    },
    {
        "name": "Sky Sports Premier League",
        "id": "skysprem",
        "logo": "https://raw.githubusercontent.com/abusaeeidx/Tv-Channel-Logo/heads/main/CricHD/runded/43-by-xfireflix.png",
        "link": "https://d15.epicquesthero.com:999/hls/skysprem.m3u8?md5=DERNuZwOk5gLrkelXjAYHw&expires=1759962398",
        "referer": "https://stylisheleg4nt.com",
        "origin": "https://stylisheleg4nt.com"
    },
    {
        "name": "Sky Sports Football",
        "id": "skysfott",
        "logo": "https://raw.githubusercontent.com/abusaeeidx/Tv-Channel-Logo/heads/main/CricHD/runded/44-by-xfireflix.png",
        "link": "https://d15.epicquesthero.com:999/hls/skysfott.m3u8?md5=xltWkF53wMXoZp3vWI2RYA&expires=1759962398",
        "referer": "https://stylisheleg4nt.com",
        "origin": "https://stylisheleg4nt.com"
    },
    {
        "name": "Sky Sports Plus",
        "id": "skysare",
        "logo": "https://raw.githubusercontent.com/abusaeeidx/Tv-Channel-Logo/heads/main/CricHD/runded/1745008347584.png",
        "link": "https://d15.epicquesthero.com:999/hls/skysare.m3u8?md5=1CbVCkD96Xd38L6RhuQXbA&expires=1759962398",
        "referer": "https://stylisheleg4nt.com",
        "origin": "https://stylisheleg4nt.com"
    },
    {
        "name": "Sky Sports F1",
        "id": "skysfor1",
        "logo": "https://raw.githubusercontent.com/abusaeeidx/Tv-Channel-Logo/heads/main/CricHD/runded/1745008468637.png",
        "link": "https://d15.epicquesthero.com:999/hls/skysfor1.m3u8?md5=jq_z2ytLzUy3LITqj5RJMw&expires=1759962398",
        "referer": "https://stylisheleg4nt.com",
        "origin": "https://stylisheleg4nt.com"
    },
    {
        "name": "LaLiGA",
        "id": "laligauk",
        "logo": "https://raw.githubusercontent.com/abusaeeidx/Tv-Channel-Logo/heads/main/CricHD/runded/19-by-xfireflix.png",
        "link": "https://d15.epicquesthero.com:999/hls/laligauk.m3u8?md5=M5Tyt1Z97M1WTLvwzCXqtw&expires=1759962398",
        "referer": "https://stylisheleg4nt.com",
        "origin": "https://stylisheleg4nt.com"
    },
    {
        "name": "Premier Sports 1",
        "id": "premieruk",
        "logo": "https://raw.githubusercontent.com/abusaeeidx/Tv-Channel-Logo/heads/main/CricHD/runded/31-by-xfireflix.png",
        "link": "https://d15.epicquesthero.com:999/hls/premieruk.m3u8?md5=O8hDHkpmzkigo5oJqGtemw&expires=1759962398",
        "referer": "https://stylisheleg4nt.com",
        "origin": "https://stylisheleg4nt.com"
    },
    {
        "name": "Premier Sports 2",
        "id": "hdchnl2",
        "logo": "https://raw.githubusercontent.com/abusaeeidx/Tv-Channel-Logo/heads/main/CricHD/runded/31-by-xfireflix.png",
        "link": "https://d15.epicquesthero.com:999/hls/hdchnl2.m3u8?md5=I9tvAU8Xbmdko2m8wHCEDQ&expires=1759962398",
        "referer": "https://stylisheleg4nt.com",
        "origin": "https://stylisheleg4nt.com"
    },
    {
        "name": "Super Football",
        "id": "superfotball",
        "logo": "https://raw.githubusercontent.com/abusaeeidx/Tv-Channel-Logo/heads/main/CricHD/runded/34-by-xfireflix.png",
        "link": "https://d15.epicquesthero.com:999/hls/superfotball.m3u8?md5=TWWNEI2RNznc71FsEkrGbg&expires=1759962398",
        "referer": "https://stylisheleg4nt.com",
        "origin": "https://stylisheleg4nt.com"
    },
    {
        "name": "Super Premier League",
        "id": "superpremier",
        "logo": "https://raw.githubusercontent.com/abusaeeidx/Tv-Channel-Logo/heads/main/CricHD/runded/1745008781606.png",
        "link": "https://d15.epicquesthero.com:999/hls/superpremier.m3u8?md5=ToRySUMsZG-W89Mia4lDJw&expires=1759962398",
        "referer": "https://stylisheleg4nt.com",
        "origin": "https://stylisheleg4nt.com"
    },
    {
        "name": "Astro Cricket",
        "id": "fox501",
        "logo": "https://raw.githubusercontent.com/abusaeeidx/Tv-Channel-Logo/heads/main/CricHD/runded/1745008895589.png",
        "link": "https://d15.epicquesthero.com:999/hls/fox501.m3u8?md5=4GeKmJ1EjVBy2hVhAFj6DA&expires=1759962399",
        "referer": "https://stylisheleg4nt.com",
        "origin": "https://stylisheleg4nt.com"
    },
    {
        "name": "ESPN 1",
        "id": "espnusa",
        "logo": "https://raw.githubusercontent.com/abusaeeidx/Tv-Channel-Logo/heads/main/CricHD/runded/17-by-xfireflix.png",
        "link": "https://d15.epicquesthero.com:999/hls/espnusa.m3u8?md5=o9r8pYPCeLtZOt8wOySiuA&expires=1759962399",
        "referer": "https://stylisheleg4nt.com",
        "origin": "https://stylisheleg4nt.com"
    },
    {
        "name": "ESPN 2",
        "id": "espn2",
        "logo": "https://raw.githubusercontent.com/abusaeeidx/Tv-Channel-Logo/heads/main/CricHD/runded/17-by-xfireflix.png",
        "link": "https://d15.epicquesthero.com:999/hls/espn2.m3u8?md5=ZoKRhvlIEzEzzUri_tvfTA&expires=1759962399",
        "referer": "https://stylisheleg4nt.com",
        "origin": "https://stylisheleg4nt.com"
    },
    {
        "name": "Sky Sports Arena",
        "id": "skysare",
        "logo": "https://raw.githubusercontent.com/abusaeeidx/Tv-Channel-Logo/heads/main/CricHD/runded/1745007829327.png",
        "link": "https://d15.epicquesthero.com:999/hls/skysare.m3u8?md5=S_8MZZrYFsRZN2oxAVm9Zw&expires=1759962399",
        "referer": "https://stylisheleg4nt.com",
        "origin": "https://stylisheleg4nt.com"
    },
    {
        "name": "Sky Sports Mix",
        "id": "skysmixx",
        "logo": "https://raw.githubusercontent.com/abusaeeidx/Tv-Channel-Logo/heads/main/CricHD/runded/13-by-xfireflix.png",
        "link": "https://d15.epicquesthero.com:999/hls/skysmixx.m3u8?md5=QeOVfX76vB4GBTFjLGdEkw&expires=1759962399",
        "referer": "https://stylisheleg4nt.com",
        "origin": "https://stylisheleg4nt.com"
    },
    {
        "name": "Sky Sports Tennis",
        "id": "skystennis",
        "logo": "https://raw.githubusercontent.com/abusaeeidx/Tv-Channel-Logo/heads/main/CricHD/runded/1745009085794.png",
        "link": "https://d15.epicquesthero.com:999/hls/skystennis.m3u8?md5=6vgSINqjs2Q_if9h-Ayjzg&expires=1759962399",
        "referer": "https://stylisheleg4nt.com",
        "origin": "https://stylisheleg4nt.com"
    },
    {
        "name": "Fox Cricket 501 HD",
        "id": "fox501",
        "logo": "https://raw.githubusercontent.com/abusaeeidx/Tv-Channel-Logo/heads/main/CricHD/runded/6-by-xfireflix.png",
        "link": "https://d15.epicquesthero.com:999/hls/fox501.m3u8?md5=4GeKmJ1EjVBy2hVhAFj6DA&expires=1759962399",
        "referer": "https://stylisheleg4nt.com",
        "origin": "https://stylisheleg4nt.com"
    },
    {
        "name": "Sony Sports3",
        "id": "ten1hd",
        "logo": "https://raw.githubusercontent.com/abusaeeidx/Tv-Channel-Logo/heads/main/CricHD/runded/1000173192-modified.png",
        "link": "https://d15.epicquesthero.com:999/hls/ten1hd.m3u8?md5=vJO-3OjhFdikEAdJeb5l6Q&expires=1759962399",
        "referer": "https://stylisheleg4nt.com",
        "origin": "https://stylisheleg4nt.com"
    }
]